README.md
setup.py
amara3.iri.egg-info/PKG-INFO
amara3.iri.egg-info/SOURCES.txt
amara3.iri.egg-info/dependency_links.txt
amara3.iri.egg-info/requires.txt
amara3.iri.egg-info/top_level.txt
pylib/__init__.py
pylib/asynctools.py
pylib/inputsource.py
pylib/iri.py
pylib/irihelper.py
pylib/util.py
pylib/version.py
pylib/contrib/__init__.py
pylib/contrib/mem_check.py
test/test_inputsource.py
test/test_iri.py